[
  {
    "id": "h-7f5e32b3",
    "title": "Community Immunisation Clinic - Mitchelton",
    "date": "08 MAR 2026",
    "venue": "Mitchelton Library",
    "hero": "https://www.trumba.com/i/DgD9EIIw6UGExwaxXK-cOmB9.jpg",
    "link": "https://www.brisbane.qld.gov.au/trumba?trumbaEmbed=view%3devent%26eventid%3d194726372",
    "source": "BCC",
    "updatedLabel": "Verified",
    "priceBand": "TBC",
    "energy": "MEDIUM",
    "indoor": "INDOOR",
    "distanceKm": 0,
    "hotScore": 85,
    "vibe": "CHILL"
  },
  {
    "id": "h-7ae41d05",
    "title": "Strength, mobility and balance",
    "date": "08 MAR 2026",
    "venue": "King Street Park, Kuraby",
    "hero": "https://www.trumba.com/i/DgB1LTFXcqbvqu9wmC8T2IjM.jpg",
    "link": "https://www.brisbane.qld.gov.au/trumba?trumbaEmbed=view%3devent%26eventid%3d183040119",
    "source": "BCC",
    "updatedLabel": "Verified",
    "priceBand": "FREE",
    "energy": "MEDIUM",
    "indoor": "OUTDOOR",
    "distanceKm": 0,
    "hotScore": 95,
    "vibe": "CHILL"
  },
  {
    "id": "h-93cbbe56",
    "title": "Tai Chi Qigong",
    "date": "08 MAR 2026",
    "venue": "Keating Park, Indooroopilly",
    "hero": "https://www.trumba.com/i/DgAUxiPaK2PVMUWQWZLBGhCg.jpg",
    "link": "https://www.brisbane.qld.gov.au/trumba?trumbaEmbed=view%3devent%26eventid%3d183040296",
    "source": "BCC",
    "updatedLabel": "Verified",
    "priceBand": "BUDGET",
    "energy": "LOW",
    "indoor": "OUTDOOR",
    "distanceKm": 0,
    "hotScore": 85,
    "vibe": "CHILL"
  },
  {
    "id": "h-ebea738d",
    "title": "Children\u2019s storytime in the park -",
    "date": "08 MAR 2026",
    "venue": "Svoboda Park, Kuraby",
    "hero": "https://www.trumba.com/i/DgAVzxUJKOnIiA8RbMzjLr3p.jpg",
    "link": "https://www.brisbane.qld.gov.au/trumba?trumbaEmbed=view%3devent%26eventid%3d195058669",
    "source": "BCC",
    "updatedLabel": "Verified",
    "priceBand": "FREE",
    "energy": "MEDIUM",
    "indoor": "OUTDOOR",
    "distanceKm": 0,
    "hotScore": 98,
    "vibe": "CHILL"
  },
  {
    "id": "h-c999c9a0",
    "title": "Gentle fitness and  Tai-chair",
    "date": "12 MAR 2026",
    "venue": "Saint Bartholomew's Hall, 1357 Logan Road, Mount Gravatt",
    "hero": "https://www.trumba.com/i/DgD3jTxd4GeTDl1Kkz0vV1ki.jpeg",
    "link": "https://www.brisbane.qld.gov.au/trumba?trumbaEmbed=view%3devent%26eventid%3d183503535",
    "source": "BCC",
    "updatedLabel": "Verified",
    "priceBand": "FREE",
    "energy": "LOW",
    "indoor": "ANY",
    "distanceKm": 0,
    "hotScore": 93,
    "vibe": "SPORTS"
  },
  {
    "id": "h-90ce9685",
    "title": "Alliance Francaise French Film Festival",
    "date": "12 MAR 2026",
    "venue": "Venue TBC",
    "hero": "https://www.trumba.com/i/DgDmW8ee7KPWV25LBwtVkiin.jpg",
    "link": "https://www.brisbane.qld.gov.au/trumba?trumbaEmbed=view%3devent%26eventid%3d197602505",
    "source": "BCC",
    "updatedLabel": "Verified",
    "priceBand": "TBC",
    "energy": "HIGH",
    "indoor": "ANY",
    "distanceKm": 0,
    "hotScore": 84,
    "vibe": "MUSIC"
  },
  {
    "id": "h-0e4f94e4",
    "title": "An intimate evening with Celtic Thunder: A celebration of their greatest songs",
    "date": "13 MAR 2026",
    "venue": "Brisbane Convention & Exhibition Centre, Southbank",
    "hero": "https://www.trumba.com/i/DgCuksXLjoNjhypnWLGbOQ16.jpg",
    "link": "https://www.brisbane.qld.gov.au/trumba?trumbaEmbed=view%3devent%26eventid%3d196189784",
    "source": "BCC",
    "updatedLabel": "Verified",
    "priceBand": "TBC",
    "energy": "MEDIUM",
    "indoor": "INDOOR",
    "distanceKm": 0,
    "hotScore": 86,
    "vibe": "CHILL"
  },
  {
    "id": "h-d8e84916",
    "title": "Faur\u00e9 Requiem",
    "date": "14 MAR 2026",
    "venue": "Venue TBC",
    "hero": "https://www.trumba.com/i/DgCQ-MLhXJZ6HvieSF0ULGen.jpg",
    "link": "https://www.brisbane.qld.gov.au/trumba?trumbaEmbed=view%3devent%26eventid%3d197419895",
    "source": "BCC",
    "updatedLabel": "Verified",
    "priceBand": "PREMIUM",
    "energy": "MEDIUM",
    "indoor": "INDOOR",
    "distanceKm": 0,
    "hotScore": 80,
    "vibe": "CHILL"
  },
  {
    "id": "h-90ce9685",
    "title": "Alliance Francaise French Film Festival",
    "date": "14 MAR 2026",
    "venue": "Venue TBC",
    "hero": "https://www.trumba.com/i/DgDmW8ee7KPWV25LBwtVkiin.jpg",
    "link": "https://www.brisbane.qld.gov.au/trumba?trumbaEmbed=view%3devent%26eventid%3d197602507",
    "source": "BCC",
    "updatedLabel": "Verified",
    "priceBand": "TBC",
    "energy": "HIGH",
    "indoor": "ANY",
    "distanceKm": 0,
    "hotScore": 84,
    "vibe": "MUSIC"
  },
  {
    "id": "h-5bae7b54",
    "title": "Orienteering",
    "date": "14 MAR 2026",
    "venue": "Sergeant Dan Stiller Memorial Reserve, Heathwood",
    "hero": "https://www.trumba.com/i/DgDNs0nhEy4B2%2AciqjiWfWLW.jpg",
    "link": "https://www.brisbane.qld.gov.au/trumba?trumbaEmbed=view%3devent%26eventid%3d182849686",
    "source": "BCC",
    "updatedLabel": "Verified",
    "priceBand": "BUDGET",
    "energy": "LOW",
    "indoor": "OUTDOOR",
    "distanceKm": 0,
    "hotScore": 94,
    "vibe": "CHILL"
  },
  {
    "id": "h-f9e48de1",
    "title": "MacArthur Museum - New exhibition on Prisoners of War",
    "date": "15 MAR 2026",
    "venue": "Venue TBC",
    "hero": "https://www.trumba.com/i/DgDaQWx9hu2am5l7XJ9cfRq3.jpg",
    "link": "https://www.brisbane.qld.gov.au/trumba?trumbaEmbed=view%3devent%26eventid%3d196580202",
    "source": "BCC",
    "updatedLabel": "Verified",
    "priceBand": "BUDGET",
    "energy": "MEDIUM",
    "indoor": "INDOOR",
    "distanceKm": 0,
    "hotScore": 86,
    "vibe": "CHILL"
  },
  {
    "id": "h-90ce9685",
    "title": "Alliance Francaise French Film Festival",
    "date": "17 MAR 2026",
    "venue": "Venue TBC",
    "hero": "https://www.trumba.com/i/DgDmW8ee7KPWV25LBwtVkiin.jpg",
    "link": "https://www.brisbane.qld.gov.au/trumba?trumbaEmbed=view%3devent%26eventid%3d197602510",
    "source": "BCC",
    "updatedLabel": "Verified",
    "priceBand": "TBC",
    "energy": "HIGH",
    "indoor": "ANY",
    "distanceKm": 0,
    "hotScore": 84,
    "vibe": "MUSIC"
  },
  {
    "id": "h-d6af4710",
    "title": "Yoga for mobility",
    "date": "10 MAR 2026",
    "venue": "John Walker Place, Yeronga",
    "hero": "https://www.trumba.com/i/DgBn-7sg-wtZpLktWji-fURD.jpg",
    "link": "https://www.brisbane.qld.gov.au/trumba?trumbaEmbed=view%3devent%26eventid%3d183181933",
    "source": "BCC",
    "updatedLabel": "Verified",
    "priceBand": "FREE",
    "energy": "LOW",
    "indoor": "OUTDOOR",
    "distanceKm": 0,
    "hotScore": 84,
    "vibe": "SPORTS"
  },
  {
    "id": "h-ec4f1af1",
    "title": "Zumba Gold\u00ae",
    "date": "17 MAR 2026",
    "venue": "O'Callaghan Park, Zillmere",
    "hero": "https://www.trumba.com/i/DgDcVA2yNc5TR0n-2aJZTjvS.jpg",
    "link": "https://www.brisbane.qld.gov.au/trumba?trumbaEmbed=view%3devent%26eventid%3d183181653",
    "source": "BCC",
    "updatedLabel": "Verified",
    "priceBand": "FREE",
    "energy": "MEDIUM",
    "indoor": "OUTDOOR",
    "distanceKm": 0,
    "hotScore": 91,
    "vibe": "CHILL"
  },
  {
    "id": "h-8be1c94f",
    "title": "Yoga",
    "date": "10 MAR 2026",
    "venue": "Kalinga Park, Kalinga",
    "hero": "https://www.trumba.com/i/DgDET0gY-pw4UiS%2AkruScJyW.jpg",
    "link": "https://www.brisbane.qld.gov.au/trumba?trumbaEmbed=view%3devent%26eventid%3d183185848",
    "source": "BCC",
    "updatedLabel": "Verified",
    "priceBand": "FREE",
    "energy": "LOW",
    "indoor": "OUTDOOR",
    "distanceKm": 0,
    "hotScore": 89,
    "vibe": "SPORTS"
  },
  {
    "id": "h-93cbbe56",
    "title": "Tai Chi Qigong",
    "date": "10 MAR 2026",
    "venue": "Akuna Street Park, Kenmore",
    "hero": "https://www.trumba.com/i/DgDKVDumlpuK%2AUx81tRBo3Re.jpg",
    "link": "https://www.brisbane.qld.gov.au/trumba?trumbaEmbed=view%3devent%26eventid%3d183181980",
    "source": "BCC",
    "updatedLabel": "Verified",
    "priceBand": "BUDGET",
    "energy": "LOW",
    "indoor": "OUTDOOR",
    "distanceKm": 0,
    "hotScore": 85,
    "vibe": "CHILL"
  },
  {
    "id": "h-78dc0fc5",
    "title": "Music beat kids groups",
    "date": "12 MAR 2026",
    "venue": "Akuna Street Park, Kenmore",
    "hero": "https://www.trumba.com/i/DgC8i3dfQMV6ipVMHsqQFmoR.jpeg",
    "link": "https://www.brisbane.qld.gov.au/trumba?trumbaEmbed=view%3devent%26eventid%3d183232622",
    "source": "BCC",
    "updatedLabel": "Verified",
    "priceBand": "FREE",
    "energy": "MEDIUM",
    "indoor": "OUTDOOR",
    "distanceKm": 0,
    "hotScore": 98,
    "vibe": "MUSIC"
  },
  {
    "id": "h-7d42f492",
    "title": "Fun soccer",
    "date": "10 MAR 2026",
    "venue": "Ducie Street Park, Darra",
    "hero": "https://www.trumba.com/i/DgCZBh9gNKMeQx6oZCKQafk1.jpg",
    "link": "https://www.brisbane.qld.gov.au/trumba?trumbaEmbed=view%3devent%26eventid%3d183401824",
    "source": "BCC",
    "updatedLabel": "Verified",
    "priceBand": "FREE",
    "energy": "MEDIUM",
    "indoor": "OUTDOOR",
    "distanceKm": 0,
    "hotScore": 97,
    "vibe": "CHILL"
  },
  {
    "id": "h-bc58c1a1",
    "title": "Fun soccer for 2-5 years",
    "date": "10 MAR 2026",
    "venue": "Victoria Park / Barrambin, Central Parkland",
    "hero": "https://www.trumba.com/i/DgCZBh9gNKMeQx6oZCKQafk1.jpg",
    "link": "https://www.brisbane.qld.gov.au/trumba?trumbaEmbed=view%3devent%26eventid%3d183211206",
    "source": "BCC",
    "updatedLabel": "Verified",
    "priceBand": "FREE",
    "energy": "MEDIUM",
    "indoor": "OUTDOOR",
    "distanceKm": 0,
    "hotScore": 87,
    "vibe": "CHILL"
  },
  {
    "id": "h-656c7aac",
    "title": "Hot hula",
    "date": "10 MAR 2026",
    "venue": "Calamvale District Park, Calamvale",
    "hero": "https://www.trumba.com/i/DgD0w0nQg9pK1RS6XBmFbHoW.jpg",
    "link": "https://www.brisbane.qld.gov.au/trumba?trumbaEmbed=view%3devent%26eventid%3d183211540",
    "source": "BCC",
    "updatedLabel": "Verified",
    "priceBand": "FREE",
    "energy": "MEDIUM",
    "indoor": "OUTDOOR",
    "distanceKm": 0,
    "hotScore": 80,
    "vibe": "CHILL"
  },
  {
    "id": "h-a1a41068",
    "title": "Zumba\u00ae",
    "date": "14 MAR 2026",
    "venue": "Calamvale District Park, Calamvale",
    "hero": "https://www.trumba.com/i/DgCFwhoZBXnqPDsXuk9PN0dZ.jpeg",
    "link": "https://www.brisbane.qld.gov.au/trumba?trumbaEmbed=view%3devent%26eventid%3d183335863",
    "source": "BCC",
    "updatedLabel": "Verified",
    "priceBand": "FREE",
    "energy": "MEDIUM",
    "indoor": "OUTDOOR",
    "distanceKm": 0,
    "hotScore": 98,
    "vibe": "CHILL"
  },
  {
    "id": "h-656c7aac",
    "title": "Hot hula",
    "date": "17 MAR 2026",
    "venue": "Calamvale District Park, Calamvale",
    "hero": "https://www.trumba.com/i/DgD0w0nQg9pK1RS6XBmFbHoW.jpg",
    "link": "https://www.brisbane.qld.gov.au/trumba?trumbaEmbed=view%3devent%26eventid%3d183211541",
    "source": "BCC",
    "updatedLabel": "Verified",
    "priceBand": "FREE",
    "energy": "MEDIUM",
    "indoor": "OUTDOOR",
    "distanceKm": 0,
    "hotScore": 80,
    "vibe": "CHILL"
  },
  {
    "id": "h-75ea26e8",
    "title": "Mums and bubs babywearing fitness",
    "date": "17 MAR 2026",
    "venue": "Colmslie Beach Reserve, Murarrie",
    "hero": "https://www.trumba.com/i/DgDmE7sFdxwkqiQ-fxWeQ30E.jpg",
    "link": "https://www.brisbane.qld.gov.au/trumba?trumbaEmbed=view%3devent%26eventid%3d183211725",
    "source": "BCC",
    "updatedLabel": "Verified",
    "priceBand": "FREE",
    "energy": "MEDIUM",
    "indoor": "OUTDOOR",
    "distanceKm": 0,
    "hotScore": 87,
    "vibe": "SPORTS"
  },
  {
    "id": "h-88925811",
    "title": "Mums and bubs yoga",
    "date": "10 MAR 2026",
    "venue": "Teralba Park, Everton Park",
    "hero": "https://www.trumba.com/i/DgA3dq-6ZJ7CcAztY3JzswOW.jpg",
    "link": "https://www.brisbane.qld.gov.au/trumba?trumbaEmbed=view%3devent%26eventid%3d183212236",
    "source": "BCC",
    "updatedLabel": "Verified",
    "priceBand": "FREE",
    "energy": "LOW",
    "indoor": "OUTDOOR",
    "distanceKm": 0,
    "hotScore": 80,
    "vibe": "SPORTS"
  },
  {
    "id": "h-ebea738d",
    "title": "Children\u2019s storytime in the park -",
    "date": "11 MAR 2026",
    "venue": "Rocks Riverside Park, Seventeen Mile Rocks",
    "hero": "https://www.trumba.com/i/DgAVzxUJKOnIiA8RbMzjLr3p.jpg",
    "link": "https://www.brisbane.qld.gov.au/trumba?trumbaEmbed=view%3devent%26eventid%3d195058834",
    "source": "BCC",
    "updatedLabel": "Verified",
    "priceBand": "FREE",
    "energy": "MEDIUM",
    "indoor": "OUTDOOR",
    "distanceKm": 0,
    "hotScore": 98,
    "vibe": "CHILL"
  },
  {
    "id": "h-965f04b1",
    "title": "U-Jam",
    "date": "12 MAR 2026",
    "venue": "Rocks Riverside Park, Seventeen Mile Rocks",
    "hero": "https://www.trumba.com/i/DgBazK0qvLKF%2ASR3VORGk%2AVK.jpeg",
    "link": "https://www.brisbane.qld.gov.au/trumba?trumbaEmbed=view%3devent%26eventid%3d183286747",
    "source": "BCC",
    "updatedLabel": "Verified",
    "priceBand": "FREE",
    "energy": "MEDIUM",
    "indoor": "ANY",
    "distanceKm": 0,
    "hotScore": 87,
    "vibe": "CHILL"
  },
  {
    "id": "h-29206867",
    "title": "Strength and cardio",
    "date": "18 MAR 2026",
    "venue": "Rocks Riverside Park, Seventeen Mile Rocks",
    "hero": "https://www.trumba.com/i/DgCdDqEiMtUURvHDiUKzx60x.jpeg",
    "link": "https://www.brisbane.qld.gov.au/trumba?trumbaEmbed=view%3devent%26eventid%3d183182847",
    "source": "BCC",
    "updatedLabel": "Verified",
    "priceBand": "FREE",
    "energy": "MEDIUM",
    "indoor": "ANY",
    "distanceKm": 0,
    "hotScore": 97,
    "vibe": "CHILL"
  },
  {
    "id": "h-7d78543c",
    "title": "Little Artist\u2019s Eye Spy",
    "date": "11 MAR 2026",
    "venue": "Museum of Brisbane, Brisbane City",
    "hero": "https://www.trumba.com/i/DgDd7Os4YYIDbYGY9dqLDhED.jpg",
    "link": "https://www.brisbane.qld.gov.au/trumba?trumbaEmbed=view%3devent%26eventid%3d194328175",
    "source": "BCC",
    "updatedLabel": "Verified",
    "priceBand": "FREE",
    "energy": "MEDIUM",
    "indoor": "INDOOR",
    "distanceKm": 0,
    "hotScore": 98,
    "vibe": "CHILL"
  },
  {
    "id": "h-7d78543c",
    "title": "Little Artist\u2019s Eye Spy",
    "date": "12 MAR 2026",
    "venue": "Museum of Brisbane, Brisbane City",
    "hero": "https://www.trumba.com/i/DgDd7Os4YYIDbYGY9dqLDhED.jpg",
    "link": "https://www.brisbane.qld.gov.au/trumba?trumbaEmbed=view%3devent%26eventid%3d194328176",
    "source": "BCC",
    "updatedLabel": "Verified",
    "priceBand": "FREE",
    "energy": "MEDIUM",
    "indoor": "INDOOR",
    "distanceKm": 0,
    "hotScore": 98,
    "vibe": "CHILL"
  },
  {
    "id": "h-88961cff",
    "title": "Clock Tower Tour",
    "date": "12 MAR 2026",
    "venue": "Museum of Brisbane, Brisbane City",
    "hero": "https://www.trumba.com/i/DgAgRyQ1NZd-GXL3xyckhMbw.jpg",
    "link": "https://www.brisbane.qld.gov.au/trumba?trumbaEmbed=view%3devent%26eventid%3d181368036",
    "source": "BCC",
    "updatedLabel": "Verified",
    "priceBand": "FREE",
    "energy": "MEDIUM",
    "indoor": "INDOOR",
    "distanceKm": 0,
    "hotScore": 96,
    "vibe": "CHILL"
  },
  {
    "id": "h-5b37262b",
    "title": "Stories You Wear: Magpie Goose",
    "date": "12 MAR 2026",
    "venue": "Museum of Brisbane, Brisbane City",
    "hero": "https://www.trumba.com/i/DgA5soPlfekhzXEIz5KAW8Xe.jpg",
    "link": "https://www.brisbane.qld.gov.au/trumba?trumbaEmbed=view%3devent%26eventid%3d192631636",
    "source": "BCC",
    "updatedLabel": "Verified",
    "priceBand": "FREE",
    "energy": "MEDIUM",
    "indoor": "INDOOR",
    "distanceKm": 0,
    "hotScore": 86,
    "vibe": "CHILL"
  },
  {
    "id": "h-88961cff",
    "title": "Clock Tower Tour",
    "date": "13 MAR 2026",
    "venue": "Museum of Brisbane, Brisbane City",
    "hero": "https://www.trumba.com/i/DgAgRyQ1NZd-GXL3xyckhMbw.jpg",
    "link": "https://www.brisbane.qld.gov.au/trumba?trumbaEmbed=view%3devent%26eventid%3d181368037",
    "source": "BCC",
    "updatedLabel": "Verified",
    "priceBand": "FREE",
    "energy": "MEDIUM",
    "indoor": "INDOOR",
    "distanceKm": 0,
    "hotScore": 96,
    "vibe": "CHILL"
  },
  {
    "id": "h-5b37262b",
    "title": "Stories You Wear: Magpie Goose",
    "date": "13 MAR 2026",
    "venue": "Museum of Brisbane, Brisbane City",
    "hero": "https://www.trumba.com/i/DgA5soPlfekhzXEIz5KAW8Xe.jpg",
    "link": "https://www.brisbane.qld.gov.au/trumba?trumbaEmbed=view%3devent%26eventid%3d192631637",
    "source": "BCC",
    "updatedLabel": "Verified",
    "priceBand": "FREE",
    "energy": "MEDIUM",
    "indoor": "INDOOR",
    "distanceKm": 0,
    "hotScore": 86,
    "vibe": "CHILL"
  },
  {
    "id": "h-7d78543c",
    "title": "Little Artist\u2019s Eye Spy",
    "date": "14 MAR 2026",
    "venue": "Museum of Brisbane, Brisbane City",
    "hero": "https://www.trumba.com/i/DgDd7Os4YYIDbYGY9dqLDhED.jpg",
    "link": "https://www.brisbane.qld.gov.au/trumba?trumbaEmbed=view%3devent%26eventid%3d194328178",
    "source": "BCC",
    "updatedLabel": "Verified",
    "priceBand": "FREE",
    "energy": "MEDIUM",
    "indoor": "INDOOR",
    "distanceKm": 0,
    "hotScore": 98,
    "vibe": "CHILL"
  },
  {
    "id": "h-88961cff",
    "title": "Clock Tower Tour",
    "date": "14 MAR 2026",
    "venue": "Museum of Brisbane, Brisbane City",
    "hero": "https://www.trumba.com/i/DgAgRyQ1NZd-GXL3xyckhMbw.jpg",
    "link": "https://www.brisbane.qld.gov.au/trumba?trumbaEmbed=view%3devent%26eventid%3d181368038",
    "source": "BCC",
    "updatedLabel": "Verified",
    "priceBand": "FREE",
    "energy": "MEDIUM",
    "indoor": "INDOOR",
    "distanceKm": 0,
    "hotScore": 96,
    "vibe": "CHILL"
  },
  {
    "id": "h-5b37262b",
    "title": "Stories You Wear: Magpie Goose",
    "date": "15 MAR 2026",
    "venue": "Museum of Brisbane, Brisbane City",
    "hero": "https://www.trumba.com/i/DgA5soPlfekhzXEIz5KAW8Xe.jpg",
    "link": "https://www.brisbane.qld.gov.au/trumba?trumbaEmbed=view%3devent%26eventid%3d192631639",
    "source": "BCC",
    "updatedLabel": "Verified",
    "priceBand": "FREE",
    "energy": "MEDIUM",
    "indoor": "INDOOR",
    "distanceKm": 0,
    "hotScore": 86,
    "vibe": "CHILL"
  },
  {
    "id": "h-5b37262b",
    "title": "Stories You Wear: Magpie Goose",
    "date": "17 MAR 2026",
    "venue": "Museum of Brisbane, Brisbane City",
    "hero": "https://www.trumba.com/i/DgA5soPlfekhzXEIz5KAW8Xe.jpg",
    "link": "https://www.brisbane.qld.gov.au/trumba?trumbaEmbed=view%3devent%26eventid%3d192631641",
    "source": "BCC",
    "updatedLabel": "Verified",
    "priceBand": "FREE",
    "energy": "MEDIUM",
    "indoor": "INDOOR",
    "distanceKm": 0,
    "hotScore": 86,
    "vibe": "CHILL"
  },
  {
    "id": "h-7d78543c",
    "title": "Little Artist\u2019s Eye Spy",
    "date": "18 MAR 2026",
    "venue": "Museum of Brisbane, Brisbane City",
    "hero": "https://www.trumba.com/i/DgDd7Os4YYIDbYGY9dqLDhED.jpg",
    "link": "https://www.brisbane.qld.gov.au/trumba?trumbaEmbed=view%3devent%26eventid%3d194328182",
    "source": "BCC",
    "updatedLabel": "Verified",
    "priceBand": "FREE",
    "energy": "MEDIUM",
    "indoor": "INDOOR",
    "distanceKm": 0,
    "hotScore": 98,
    "vibe": "CHILL"
  },
  {
    "id": "h-0d15e3d2",
    "title": "RQAS Young Artist Award",
    "date": "12 MAR 2026",
    "venue": "Petrie Terrace Gallery, Petrie Terrace",
    "hero": "https://www.trumba.com/i/DgDwKc7BBiiRYvBS-RhICXN4.jpg",
    "link": "https://www.brisbane.qld.gov.au/trumba?trumbaEmbed=view%3devent%26eventid%3d195574810",
    "source": "BCC",
    "updatedLabel": "Verified",
    "priceBand": "FREE",
    "energy": "HIGH",
    "indoor": "ANY",
    "distanceKm": 0,
    "hotScore": 88,
    "vibe": "CHILL"
  },
  {
    "id": "h-0d15e3d2",
    "title": "RQAS Young Artist Award",
    "date": "14 MAR 2026",
    "venue": "Petrie Terrace Gallery, Petrie Terrace",
    "hero": "https://www.trumba.com/i/DgDwKc7BBiiRYvBS-RhICXN4.jpg",
    "link": "https://www.brisbane.qld.gov.au/trumba?trumbaEmbed=view%3devent%26eventid%3d195574812",
    "source": "BCC",
    "updatedLabel": "Verified",
    "priceBand": "FREE",
    "energy": "HIGH",
    "indoor": "ANY",
    "distanceKm": 0,
    "hotScore": 88,
    "vibe": "CHILL"
  },
  {
    "id": "h-7a113af1",
    "title": "VolleyslamangattaDetails",
    "date": "06-15 MAR 2026",
    "venue": "Gold Coast",
    "hero": "https://www.whatsongoldcoast.au/files/content/events/v/14/all-events/gold-coast-volleyslam-68f01c6da0c751e75c1276f0/mainimage.jpg?w=1200",
    "link": "https://www.whatsongoldcoast.au/All-events/Gold-Coast-Volleyslam-68f01c6da0c751e75c1276f0",
    "source": "GCCC",
    "updatedLabel": "Verified",
    "priceBand": "TBC",
    "energy": "HIGH",
    "indoor": "OUTDOOR",
    "distanceKm": 0,
    "hotScore": 79,
    "vibe": "SPORTS"
  },
  {
    "id": "h-fa7c07af",
    "title": "Festival of Golf",
    "date": "19 MAR 2026",
    "venue": "Hope Island",
    "hero": "https://www.whatsongoldcoast.au/files/content/events/v/4/all-events/festival-of-golf-696d524ad16f929246955ed6/mainimage.jpg?w=1200",
    "link": "https://www.whatsongoldcoast.au/All-events/Festival-of-Golf-696d524ad16f929246955ed6",
    "source": "GCCC",
    "updatedLabel": "Verified",
    "priceBand": "TBC",
    "energy": "MEDIUM",
    "indoor": "ANY",
    "distanceKm": 0,
    "hotScore": 82,
    "vibe": "SPORTS"
  },
  {
    "id": "h-295ed977",
    "title": "The Betty Diamond Bowlapalooza",
    "date": "19 APR 2026",
    "venue": "Tugun",
    "hero": "https://www.whatsongoldcoast.au/files/content/mycity/v/7/events/the-betty-diamond-bowlapalooza/shoutout-festival_event-stills-057.jpg?w=1200",
    "link": "https://www.whatsongoldcoast.au/All-events/The-Betty-Diamond-Bowlapalooza",
    "source": "GCCC",
    "updatedLabel": "Verified",
    "priceBand": "TBC",
    "energy": "MEDIUM",
    "indoor": "ANY",
    "distanceKm": 0,
    "hotScore": 89,
    "vibe": "DEFAULT"
  },
  {
    "id": "h-97be99ed",
    "title": "Blues on",
    "date": "14 MAY 2026",
    "venue": "Broadbeach",
    "hero": "https://www.whatsongoldcoast.au/files/content/events/v/22/all-events/blues-on-broadbeach-5fc743f2ec915dfe33f18a2b/mainimage.jpg?w=1200",
    "link": "https://www.whatsongoldcoast.au/All-events/Blues-on-Broadbeach-5fc743f2ec915dfe33f18a2b",
    "source": "GCCC",
    "updatedLabel": "Verified",
    "priceBand": "TBC",
    "energy": "MEDIUM",
    "indoor": "OUTDOOR",
    "distanceKm": 0,
    "hotScore": 79,
    "vibe": "DEFAULT"
  },
  {
    "id": "h-e0892964",
    "title": "Gold Coast Volleyslam",
    "date": "06 MAR 2026",
    "venue": "Coolangatta",
    "hero": "https://www.whatsongoldcoast.au/files/content/events/v/14/all-events/gold-coast-volleyslam-68f01c6da0c751e75c1276f0/mainimage.jpg?w=1200",
    "link": "https://www.whatsongoldcoast.au/All-events/Gold-Coast-Volleyslam-68f01c6da0c751e75c1276f0",
    "source": "GCCC",
    "updatedLabel": "Verified",
    "priceBand": "TBC",
    "energy": "HIGH",
    "indoor": "OUTDOOR",
    "distanceKm": 0,
    "hotScore": 73,
    "vibe": "SPORTS"
  },
  {
    "id": "h-70b8b2e3",
    "title": "Rent: The Musical",
    "date": "07 MAR 2026",
    "venue": "Nerang",
    "hero": "https://www.whatsongoldcoast.au/files/content/mycity/v/1/events/rent-the-musical/rent-whats-on.jpg?w=1200",
    "link": "https://www.whatsongoldcoast.au/All-events/Rent-The-Musical",
    "source": "GCCC",
    "updatedLabel": "Verified",
    "priceBand": "TBC",
    "energy": "MEDIUM",
    "indoor": "ANY",
    "distanceKm": 0,
    "hotScore": 93,
    "vibe": "MUSIC"
  },
  {
    "id": "h-3542b778",
    "title": "Duck Pond",
    "date": "06 MAR 2026",
    "venue": "Surfers Paradise",
    "hero": "https://www.whatsongoldcoast.au/files/content/mycity/v/1/events/duck-pond/untitled-design.png?w=1200",
    "link": "https://www.whatsongoldcoast.au/All-events/Duck-Pond",
    "source": "GCCC",
    "updatedLabel": "Verified",
    "priceBand": "TBC",
    "energy": "MEDIUM",
    "indoor": "ANY",
    "distanceKm": 0,
    "hotScore": 83,
    "vibe": "DEFAULT"
  },
  {
    "id": "h-d3b0e997",
    "title": "HOTA Farmers and Artisan Market",
    "date": "08 MAR 2026",
    "venue": "Surfers Paradise",
    "hero": "https://www.whatsongoldcoast.au/files/content/events/v/1/all-events/hota-farmers-and-artisan-market-60deb811cdcec11c46c40065/mainimage.jpg?w=1200",
    "link": "https://www.whatsongoldcoast.au/All-events/HOTA-Farmers-and-Artisan-Market-60deb811cdcec11c46c40065",
    "source": "GCCC",
    "updatedLabel": "Verified",
    "priceBand": "TBC",
    "energy": "LOW",
    "indoor": "ANY",
    "distanceKm": 0,
    "hotScore": 78,
    "vibe": "CHILL"
  },
  {
    "id": "h-7c80a98e",
    "title": "AFC Women's Asian Cup Australia \u2013 Group A \u2013 Philippines vs Korea",
    "date": "05 MAR 2026",
    "venue": "Robina",
    "hero": "https://www.whatsongoldcoast.au/files/content/events/v/31/all-events/group-a-philippines-vs-korea-republic-afc-womens-asian-cup-australia-67ff481813bac3ad21ee1851/mainimage.jpg?w=1200",
    "link": "https://www.whatsongoldcoast.au/All-events/Group-A-Philippines-vs-Korea-Republic-AFC-Womens-Asian-Cup-Australia-67ff481813bac3ad21ee1851",
    "source": "GCCC",
    "updatedLabel": "Verified",
    "priceBand": "TBC",
    "energy": "MEDIUM",
    "indoor": "ANY",
    "distanceKm": 0,
    "hotScore": 87,
    "vibe": "DEFAULT"
  },
  {
    "id": "h-56ebca68",
    "title": "Shakespeare's Titus Andronicus",
    "date": "04 MAR 2026",
    "venue": "Southport",
    "hero": "https://www.whatsongoldcoast.au/files/content/mycity/v/1/events/shakespeares-titus-andronicus/294832288_10225380969504394_4320876961421023797_n.jpeg?w=1200",
    "link": "https://www.whatsongoldcoast.au/All-events/Shakespeares-Titus-Andronicus",
    "source": "GCCC",
    "updatedLabel": "Verified",
    "priceBand": "TBC",
    "energy": "MEDIUM",
    "indoor": "INDOOR",
    "distanceKm": 0,
    "hotScore": 74,
    "vibe": "DEFAULT"
  },
  {
    "id": "h-03a46622",
    "title": "Australian Boardriders Battle \u2013 Grand Final",
    "date": "07 MAR 2026",
    "venue": "Burleigh",
    "hero": "https://www.whatsongoldcoast.au/files/content/events/v/25/all-events/australian-boardriders-battle-grand-final-688865e7ac99ebb27820da9d/mainimage.jpg?w=1200",
    "link": "https://www.whatsongoldcoast.au/All-events/Australian-Boardriders-Battle-Grand-Final-688865e7ac99ebb27820da9d",
    "source": "GCCC",
    "updatedLabel": "Verified",
    "priceBand": "TBC",
    "energy": "HIGH",
    "indoor": "ANY",
    "distanceKm": 0,
    "hotScore": 91,
    "vibe": "DEFAULT"
  },
  {
    "id": "h-7c0a9ebe",
    "title": "Australian WPGA Championship",
    "date": "19 MAR 2026",
    "venue": "Hope Island",
    "hero": "https://www.whatsongoldcoast.au/files/content/events/v/15/all-events/australian-wpga-championship-68f6aba3196baee8713c4639/mainimage.jpg?w=1200",
    "link": "https://www.whatsongoldcoast.au/All-events/Australian-WPGA-Championship-68f6aba3196baee8713c4639",
    "source": "GCCC",
    "updatedLabel": "Verified",
    "priceBand": "TBC",
    "energy": "MEDIUM",
    "indoor": "ANY",
    "distanceKm": 0,
    "hotScore": 85,
    "vibe": "DEFAULT"
  }
]